{
  "id": "90575c32-ac7d-4d55-a60c-9bd90e66e3b5",
  "name": "high_number_of_distinct_folders_opened_attempts",
  "startDate": 1407859200,
  "endDate": 1407862800,
  "anomalyValue": "3.0",
  "schema": "FILE",
  "type": "FEATURE_AGGREGATION",
  "score": 85.0,
  "historicalData": {
    "type": "TIME_AGGREGATION",
      "buckets": [
        {
          "key": 1497240000,
          "value": 1
        },
        {
          "key": 1497304800,
          "value": 1
        },
        {
          "key": 1497369600,
          "value": 1
        },
        {
          "key": 1497434400,
          "value": 1
        },
        {
          "key": 1497499200,
          "value": 1
        },
        {
          "key": 1497564000,
          "value": 1
        },
        {
          "key": 1497628800,
          "value": 1
        },
        {
          "key": 1497693600,
          "value": 1
        },
        {
          "key": 1497758400,
          "value": 1
        },
        {
          "key": 1497823200,
          "value": 1
        },
        {
          "key": 1497888000,
          "value": 1
        },
        {
          "key": 1497952800,
          "value": 1
        },
        {
          "key": 1498017600,
          "value": 1
        },
        {
          "key": 1498082400,
          "value": 1
        },
        {
          "key": 1498147200,
          "value": 1
        },
        {
          "key": 1498212000,
          "value": 1
        },
        {
          "key": 1498276800,
          "value": 1
        },
        {
          "key": 1498341600,
          "value": 1
        },
        {
          "key": 1498406400,
          "value": 1
        },
        {
          "key": 1498471200,
          "value": 1
        },
        {
          "key": 1498536000,
          "value": 1
        },
        {
          "key": 1498600800,
          "value": 1
        },
        {
          "key": 1498665600,
          "value": 1
        },
        {
          "key": 1498730400,
          "value": 1
        },
        {
          "key": 1498795200,
          "value": 1
        },
        {
          "key": 1498860000,
          "value": 0
        },
        {
          "key": 1498924800,
          "value": 0
        },
        {
          "key": 1498989600,
          "value": 0
        },
        {
          "key": 1499054400,
          "value": 0
        },
        {
          "key": 1499119200,
          "value": 0
        },
        {
          "key": 1499184000,
          "value": 0
        },
        {
          "key": 1499248800,
          "value": 0
        },
        {
          "key": 1499313600,
          "value": 0
        },
        {
          "key": 1499378400,
          "value": 0
        },
        {
          "key": 1499443200,
          "value": 0
        },
        {
          "key": 1499508000,
          "value": 0
        },
        {
          "key": 1499572800,
          "value": 0
        },
        {
          "key": 1499637600,
          "value": 0
        },
        {
          "key": 1499702400,
          "value": 0
        },
        {
          "key": 1499767200,
          "value": 0
        },
        {
          "key": 1499832000,
          "value": 0
        },
        {
          "key": 1499896800,
          "value": 0
        },
        {
          "key": 1499961600,
          "value": 0
        },
        {
          "key": 1500026400,
          "value": 0
        },
        {
          "key": 1500091200,
          "value": 0
        },
        {
          "key": 1500156000,
          "value": 0
        },
        {
          "key": 1500220800,
          "value": 0
        },
        {
          "key": 1500285600,
          "value": 0
        },
        {
          "key": 1500350400,
          "value": 0
        },
        {
          "key": 1500415200,
          "value": 0
        },
        {
          "key": 1500480000,
          "value": 0
        },
        {
          "key": 1500544800,
          "value": 0
        },
        {
          "key": 1500609600,
          "value": 0
        },
        {
          "key": 1500674400,
          "value": 0
        },
        {
          "key": 1500739200,
          "value": 0
        },
        {
          "key": 1500804000,
          "value": 0
        },
        {
          "key": 1500868800,
          "value": 0
        },
        {
          "key": 1500933600,
          "value": 0
        },
        {
          "key": 1500998400,
          "value": 0
        },
        {
          "key": 1501063200,
          "value": 0
        },
        {
          "key": 1501128000,
          "value": 0
        },
        {
          "key": 1501192800,
          "value": 0
        },
        {
          "key": 1501257600,
          "value": 0
        },
        {
          "key": 1501322400,
          "value": 0
        },
        {
          "key": 1501387200,
          "value": 0
        },
        {
          "key": 1501452000,
          "value": 0
        },
        {
          "key": 1501516800,
          "value": 0
        },
        {
          "key": 1501581600,
          "value": 0
        },
        {
          "key": 1501646400,
          "value": 0
        },
        {
          "key": 1501711200,
          "value": 0
        },
        {
          "key": 1501776000,
          "value": 0
        },
        {
          "key": 1501840800,
          "value": 0
        },
        {
          "key": 1501905600,
          "value": 0
        },
        {
          "key": 1501970400,
          "value": 0
        },
        {
          "key": 1502035200,
          "value": 0
        },
        {
          "key": 1502100000,
          "value": 0
        },
        {
          "key": 1502164800,
          "value": 0
        },
        {
          "key": 1502229600,
          "value": 0
        },
        {
          "key": 1502294400,
          "value": 0
        },
        {
          "key": 1502359200,
          "value": 0
        },
        {
          "key": 1502424000,
          "value": 0
        },
        {
          "key": 1502488800,
          "value": 0
        },
        {
          "key": 1502553600,
          "value": 0
        },
        {
          "key": 1502618400,
          "value": 0
        },
        {
          "key": 1502683200,
          "value": 0
        },
        {
          "key": 1502748000,
          "value": 0
        },
        {
          "key": 1502812800,
          "value": 0
        },
        {
          "key": 1502877600,
          "value": 0
        },
        {
          "key": 1502942400,
          "value": 0
        },
        {
          "key": 1503007200,
          "value": 5
        }
      ]
  },
  "eventsNum": 9
}