<?xml version='1.0' encoding='utf-8'?>
<job-scheduling-data
	xmlns="http://www.quartz-scheduler.org/xml/JobSchedulingData"
	xmlns:xsi="http://www.w3.org/2001/XMLSchema-instance"
	xsi:schemaLocation="http://www.quartz-scheduler.org/xml/JobSchedulingData http://www.quartz-scheduler.org/xml/job_scheduling_data_2_0.xsd"
	version="2.0">

	<schedule>
		<job>
			<name>VPN_SCORING</name>
			<group>VPN</group>
			<description>Running VPN Scoring</description>
			<job-class>fortscale.collection.scoring.jobs.VpnScoringJob</job-class>
			<durability>true</durability>
			<recover>true</recover>
			
			
		</job>
	
		<trigger>
			<cron>
				<name>VPN_SCORING_HOURLY_TRIGGER</name>
				<job-name>VPN_SCORING</job-name>
				<job-group>VPN</job-group>
				<cron-expression>1 * * * * ?</cron-expression>
			</cron>
		</trigger>
	
	</schedule>


</job-scheduling-data>