{
  "_index": ".kibana",
  "_type": "index-pattern",
  "_id": "presidio-monitoring",
  "_version": 1,
  "found": true,
  "_source": {
    "title": "presidio-monitoring",
    "timeFieldName": "timestamp",
    "fields": "[{\"name\":\"value.SYSTEM_MEM_FREE\",\"type\":\"number\",\"count\":0,\"scripted\":false,\"indexed\":true,\"analyzed\":false,\"doc_values\":true,\"searchable\":true,\"aggregatable\":true},{\"name\":\"value.NULL_FEATURE_BUCKET_ID\",\"type\":\"number\",\"count\":0,\"scripted\":false,\"indexed\":true,\"analyzed\":false,\"doc_values\":true,\"searchable\":true,\"aggregatable\":true},{\"name\":\"value.COUNT\",\"type\":\"number\",\"count\":0,\"scripted\":false,\"indexed\":true,\"analyzed\":false,\"doc_values\":true,\"searchable\":true,\"aggregatable\":true},{\"name\":\"value.AVG_GLOBAL_SD\",\"type\":\"number\",\"count\":0,\"scripted\":false,\"indexed\":true,\"analyzed\":false,\"doc_values\":true,\"searchable\":true,\"aggregatable\":true},{\"name\":\"value.SYSTEM_GC_OLD_COUNT\",\"type\":\"number\",\"count\":0,\"scripted\":false,\"indexed\":true,\"analyzed\":false,\"doc_values\":true,\"searchable\":true,\"aggregatable\":true},{\"name\":\"value.MAX_CONTINUOUS_N\",\"type\":\"number\",\"count\":0,\"scripted\":false,\"indexed\":true,\"analyzed\":false,\"doc_values\":true,\"searchable\":true,\"aggregatable\":true},{\"name\":\"value.AVG_MAX_CONTINUOUS_MAX_VALUE\",\"type\":\"number\",\"count\":0,\"scripted\":false,\"indexed\":true,\"analyzed\":false,\"doc_values\":true,\"searchable\":true,\"aggregatable\":true},{\"name\":\"value.MAX_OF_BUCKET_HITS\",\"type\":\"number\",\"count\":0,\"scripted\":false,\"indexed\":true,\"analyzed\":false,\"doc_values\":true,\"searchable\":true,\"aggregatable\":true},{\"name\":\"tags.APPLICATION_NAME\",\"type\":\"string\",\"count\":0,\"scripted\":false,\"indexed\":true,\"analyzed\":false,\"doc_values\":true,\"searchable\":true,\"aggregatable\":true},{\"name\":\"value.AMOUNT_OF_CONTEXTS_WITH_POSITIVE_BUCKET_VALUES\",\"type\":\"number\",\"count\":0,\"scripted\":false,\"indexed\":true,\"analyzed\":false,\"doc_values\":true,\"searchable\":true,\"aggregatable\":true},{\"name\":\"value.SUCCESS_EVENTS\",\"type\":\"number\",\"count\":0,\"scripted\":false,\"indexed\":true,\"analyzed\":false,\"doc_values\":true,\"searchable\":true,\"aggregatable\":true},{\"name\":\"value.MAX\",\"type\":\"number\",\"count\":0,\"scripted\":false,\"indexed\":true,\"analyzed\":false,\"doc_values\":true,\"searchable\":true,\"aggregatable\":true},{\"name\":\"value.SYSTEM_MEM\",\"type\":\"number\",\"count\":0,\"scripted\":false,\"indexed\":true,\"analyzed\":false,\"doc_values\":true,\"searchable\":true,\"aggregatable\":true},{\"name\":\"tags.IS_SYSTEM_METRIC\",\"type\":\"string\",\"count\":0,\"scripted\":false,\"indexed\":true,\"analyzed\":false,\"doc_values\":true,\"searchable\":true,\"aggregatable\":true},{\"name\":\"value.MAX_MAX_CONTINUOUS_MAX_VALUE\",\"type\":\"number\",\"count\":0,\"scripted\":false,\"indexed\":true,\"analyzed\":false,\"doc_values\":true,\"searchable\":true,\"aggregatable\":true},{\"name\":\"id\",\"type\":\"string\",\"count\":0,\"scripted\":false,\"indexed\":true,\"analyzed\":false,\"doc_values\":true,\"searchable\":true,\"aggregatable\":true},{\"name\":\"value.MIN_RESOLUTION\",\"type\":\"number\",\"count\":0,\"scripted\":false,\"indexed\":true,\"analyzed\":false,\"doc_values\":true,\"searchable\":true,\"aggregatable\":true},{\"name\":\"value.AVG_PAGE_SIZE\",\"type\":\"number\",\"count\":0,\"scripted\":false,\"indexed\":true,\"analyzed\":false,\"doc_values\":true,\"searchable\":true,\"aggregatable\":true},{\"name\":\"value.SYSTEM_GC_YOUNG_COUNT\",\"type\":\"number\",\"count\":0,\"scripted\":false,\"indexed\":true,\"analyzed\":false,\"doc_values\":true,\"searchable\":true,\"aggregatable\":true},{\"name\":\"value.AVG_RESOLUTION\",\"type\":\"number\",\"count\":0,\"scripted\":false,\"indexed\":true,\"analyzed\":false,\"doc_values\":true,\"searchable\":true,\"aggregatable\":true},{\"name\":\"value.SYSTEM_NONHEAP_USED\",\"type\":\"number\",\"count\":0,\"scripted\":false,\"indexed\":true,\"analyzed\":false,\"doc_values\":true,\"searchable\":true,\"aggregatable\":true},{\"name\":\"value.AMOUNT_OF_NON_ZERO_FEATURE_VALUES\",\"type\":\"number\",\"count\":0,\"scripted\":false,\"indexed\":true,\"analyzed\":false,\"doc_values\":true,\"searchable\":true,\"aggregatable\":true},{\"name\":\"value.SYSTEM_PROCESSORS\",\"type\":\"number\",\"count\":0,\"scripted\":false,\"indexed\":true,\"analyzed\":false,\"doc_values\":true,\"searchable\":true,\"aggregatable\":true},{\"name\":\"value.SYSTEM_HEAP_INIT\",\"type\":\"number\",\"count\":0,\"scripted\":false,\"indexed\":true,\"analyzed\":false,\"doc_values\":true,\"searchable\":true,\"aggregatable\":true},{\"name\":\"value.SYSTEM_HEAP_COMMITTED\",\"type\":\"number\",\"count\":0,\"scripted\":false,\"indexed\":true,\"analyzed\":false,\"doc_values\":true,\"searchable\":true,\"aggregatable\":true},{\"name\":\"value.SUM_MAX_CONTINUOUS_MAX_VALUE\",\"type\":\"number\",\"count\":0,\"scripted\":false,\"indexed\":true,\"analyzed\":false,\"doc_values\":true,\"searchable\":true,\"aggregatable\":true},{\"name\":\"_source\",\"type\":\"_source\",\"count\":0,\"scripted\":false,\"indexed\":false,\"analyzed\":false,\"doc_values\":false,\"searchable\":false,\"aggregatable\":false},{\"name\":\"value.HIT\",\"type\":\"number\",\"count\":0,\"scripted\":false,\"indexed\":true,\"analyzed\":false,\"doc_values\":true,\"searchable\":true,\"aggregatable\":true},{\"name\":\"value.AMOUNT_OF_NON_ZERO_SCORE\",\"type\":\"number\",\"count\":0,\"scripted\":false,\"indexed\":true,\"analyzed\":false,\"doc_values\":true,\"searchable\":true,\"aggregatable\":true},{\"name\":\"value.READS\",\"type\":\"number\",\"count\":0,\"scripted\":false,\"indexed\":true,\"analyzed\":false,\"doc_values\":true,\"searchable\":true,\"aggregatable\":true},{\"name\":\"value.TOTAL_EVENTS\",\"type\":\"number\",\"count\":0,\"scripted\":false,\"indexed\":true,\"analyzed\":false,\"doc_values\":true,\"searchable\":true,\"aggregatable\":true},{\"name\":\"value.AVG_CONTINUOUS_MEAN\",\"type\":\"number\",\"count\":0,\"scripted\":false,\"indexed\":true,\"analyzed\":false,\"doc_values\":true,\"searchable\":true,\"aggregatable\":true},{\"name\":\"value.SUM_OF_BUCKET_HITS\",\"type\":\"number\",\"count\":0,\"scripted\":false,\"indexed\":true,\"analyzed\":false,\"doc_values\":true,\"searchable\":true,\"aggregatable\":true},{\"name\":\"tags.GROUP_NAME\",\"type\":\"string\",\"count\":0,\"scripted\":false,\"indexed\":true,\"analyzed\":false,\"doc_values\":true,\"searchable\":true,\"aggregatable\":true},{\"name\":\"value.AVG_MAX_CONTINUOUS_SD\",\"type\":\"number\",\"count\":0,\"scripted\":false,\"indexed\":true,\"analyzed\":false,\"doc_values\":true,\"searchable\":true,\"aggregatable\":true},{\"name\":\"value.FAILED_EVENTS\",\"type\":\"number\",\"count\":0,\"scripted\":false,\"indexed\":true,\"analyzed\":false,\"doc_values\":true,\"searchable\":true,\"aggregatable\":true},{\"name\":\"value.SYSTEM_HEAP\",\"type\":\"number\",\"count\":0,\"scripted\":false,\"indexed\":true,\"analyzed\":false,\"doc_values\":true,\"searchable\":true,\"aggregatable\":true},{\"name\":\"tags.FEATURE_BUCKET\",\"type\":\"string\",\"count\":0,\"scripted\":false,\"indexed\":true,\"analyzed\":false,\"doc_values\":true,\"searchable\":true,\"aggregatable\":true},{\"name\":\"value.MAX_SIZE_OF_FEATURE_VALUES\",\"type\":\"number\",\"count\":0,\"scripted\":false,\"indexed\":true,\"analyzed\":false,\"doc_values\":true,\"searchable\":true,\"aggregatable\":true},{\"name\":\"value.MAX_GLOBAL_SD\",\"type\":\"number\",\"count\":0,\"scripted\":false,\"indexed\":true,\"analyzed\":false,\"doc_values\":true,\"searchable\":true,\"aggregatable\":true},{\"name\":\"value.MAX_MAX_CONTINUOUS_N\",\"type\":\"number\",\"count\":0,\"scripted\":false,\"indexed\":true,\"analyzed\":false,\"doc_values\":true,\"searchable\":true,\"aggregatable\":true},{\"name\":\"timestamp\",\"type\":\"date\",\"count\":0,\"scripted\":false,\"indexed\":true,\"analyzed\":false,\"doc_values\":true,\"searchable\":true,\"aggregatable\":true},{\"name\":\"value.SUCCESS_PAGES\",\"type\":\"number\",\"count\":0,\"scripted\":false,\"indexed\":true,\"analyzed\":false,\"doc_values\":true,\"searchable\":true,\"aggregatable\":true},{\"name\":\"value.MISS\",\"type\":\"number\",\"count\":0,\"scripted\":false,\"indexed\":true,\"analyzed\":false,\"doc_values\":true,\"searchable\":true,\"aggregatable\":true},{\"name\":\"tags.TIME\",\"type\":\"string\",\"count\":0,\"scripted\":false,\"indexed\":true,\"analyzed\":false,\"doc_values\":true,\"searchable\":true,\"aggregatable\":true},{\"name\":\"value.MAX_RESOLUTION\",\"type\":\"number\",\"count\":0,\"scripted\":false,\"indexed\":true,\"analyzed\":false,\"doc_values\":true,\"searchable\":true,\"aggregatable\":true},{\"name\":\"value.FEATURE_BUCKETS\",\"type\":\"number\",\"count\":0,\"scripted\":false,\"indexed\":true,\"analyzed\":false,\"doc_values\":true,\"searchable\":true,\"aggregatable\":true},{\"name\":\"tags.AGGREGATED_FEATURE_TYPE\",\"type\":\"string\",\"count\":0,\"scripted\":false,\"indexed\":true,\"analyzed\":false,\"doc_values\":true,\"searchable\":true,\"aggregatable\":true},{\"name\":\"tags.PID\",\"type\":\"string\",\"count\":0,\"scripted\":false,\"indexed\":true,\"analyzed\":false,\"doc_values\":true,\"searchable\":true,\"aggregatable\":true},{\"name\":\"value.SUM\",\"type\":\"number\",\"count\":0,\"scripted\":false,\"indexed\":true,\"analyzed\":false,\"doc_values\":true,\"searchable\":true,\"aggregatable\":true},{\"name\":\"value.SUM_SIZE_OF_FEATURE_VALUES\",\"type\":\"number\",\"count\":0,\"scripted\":false,\"indexed\":true,\"analyzed\":false,\"doc_values\":true,\"searchable\":true,\"aggregatable\":true},{\"name\":\"value.SUM_MAX_CONTINUOUS_N\",\"type\":\"number\",\"count\":0,\"scripted\":false,\"indexed\":true,\"analyzed\":false,\"doc_values\":true,\"searchable\":true,\"aggregatable\":true},{\"name\":\"value.SUM_CONTINUOUS_MEAN\",\"type\":\"number\",\"count\":0,\"scripted\":false,\"indexed\":true,\"analyzed\":false,\"doc_values\":true,\"searchable\":true,\"aggregatable\":true},{\"name\":\"value.MAX_CONTINUOUS_MAX_VALUE\",\"type\":\"number\",\"count\":0,\"scripted\":false,\"indexed\":true,\"analyzed\":false,\"doc_values\":true,\"searchable\":true,\"aggregatable\":true},{\"name\":\"value.SUM_CONTINUOUS_SD\",\"type\":\"number\",\"count\":0,\"scripted\":false,\"indexed\":true,\"analyzed\":false,\"doc_values\":true,\"searchable\":true,\"aggregatable\":true},{\"name\":\"tags.SCORER\",\"type\":\"string\",\"count\":0,\"scripted\":false,\"indexed\":true,\"analyzed\":false,\"doc_values\":true,\"searchable\":true,\"aggregatable\":true},{\"name\":\"value.SYSTEM_GC_YOUNG_TIME\",\"type\":\"number\",\"count\":0,\"scripted\":false,\"indexed\":true,\"analyzed\":false,\"doc_values\":true,\"searchable\":true,\"aggregatable\":true},{\"name\":\"value.SYSTEM_THREADS_PEAK\",\"type\":\"number\",\"count\":0,\"scripted\":false,\"indexed\":true,\"analyzed\":false,\"doc_values\":true,\"searchable\":true,\"aggregatable\":true},{\"name\":\"tags.ALERT_SEVERITY\",\"type\":\"string\",\"count\":0,\"scripted\":false,\"indexed\":true,\"analyzed\":false,\"doc_values\":true,\"searchable\":true,\"aggregatable\":true},{\"name\":\"value.SUM_OF_SMOOTHED_BUCKETS\",\"type\":\"number\",\"count\":0,\"scripted\":false,\"indexed\":true,\"analyzed\":false,\"doc_values\":true,\"searchable\":true,\"aggregatable\":true},{\"name\":\"value.AVG_MAX_CONTINUOUS_MEAN\",\"type\":\"number\",\"count\":0,\"scripted\":false,\"indexed\":true,\"analyzed\":false,\"doc_values\":true,\"searchable\":true,\"aggregatable\":true},{\"name\":\"value.SYSTEM_UPTIME\",\"type\":\"number\",\"count\":0,\"scripted\":false,\"indexed\":true,\"analyzed\":false,\"doc_values\":true,\"searchable\":true,\"aggregatable\":true},{\"name\":\"value.SYSTEM_HEAP_USED\",\"type\":\"number\",\"count\":0,\"scripted\":false,\"indexed\":true,\"analyzed\":false,\"doc_values\":true,\"searchable\":true,\"aggregatable\":true},{\"name\":\"tags.HOST\",\"type\":\"string\",\"count\":0,\"scripted\":false,\"indexed\":true,\"analyzed\":false,\"doc_values\":true,\"searchable\":true,\"aggregatable\":true},{\"name\":\"tags.ALERT_CLASSIFICATION\",\"type\":\"string\",\"count\":0,\"scripted\":false,\"indexed\":true,\"analyzed\":false,\"doc_values\":true,\"searchable\":true,\"aggregatable\":true},{\"name\":\"tags.GC_YOUNG_COLLECTOR\",\"type\":\"string\",\"count\":0,\"scripted\":false,\"indexed\":true,\"analyzed\":false,\"doc_values\":true,\"searchable\":true,\"aggregatable\":true},{\"name\":\"tags.GC_OLD_COLLECTOR\",\"type\":\"string\",\"count\":0,\"scripted\":false,\"indexed\":true,\"analyzed\":false,\"doc_values\":true,\"searchable\":true,\"aggregatable\":true},{\"name\":\"tags.HOUR_CLOSED\",\"type\":\"string\",\"count\":0,\"scripted\":false,\"indexed\":true,\"analyzed\":false,\"doc_values\":true,\"searchable\":true,\"aggregatable\":true},{\"name\":\"value.SYSTEM_NONHEAP_INIT\",\"type\":\"number\",\"count\":0,\"scripted\":false,\"indexed\":true,\"analyzed\":false,\"doc_values\":true,\"searchable\":true,\"aggregatable\":true},{\"name\":\"value.SYSTEM_THREADS_TOTAL_STARTED\",\"type\":\"number\",\"count\":0,\"scripted\":false,\"indexed\":true,\"analyzed\":false,\"doc_values\":true,\"searchable\":true,\"aggregatable\":true},{\"name\":\"value.AMOUNT_OF_FAILED_MODELS\",\"type\":\"number\",\"count\":0,\"scripted\":false,\"indexed\":true,\"analyzed\":false,\"doc_values\":true,\"searchable\":true,\"aggregatable\":true},{\"name\":\"value.SUM_CONTINUOUS_MAX_VALUE\",\"type\":\"number\",\"count\":0,\"scripted\":false,\"indexed\":true,\"analyzed\":false,\"doc_values\":true,\"searchable\":true,\"aggregatable\":true},{\"name\":\"value.MAX_MAX_CONTINUOUS_MEAN\",\"type\":\"number\",\"count\":0,\"scripted\":false,\"indexed\":true,\"analyzed\":false,\"doc_values\":true,\"searchable\":true,\"aggregatable\":true},{\"name\":\"value.SUM_NUM_OF_PARTITIONS\",\"type\":\"number\",\"count\":0,\"scripted\":false,\"indexed\":true,\"analyzed\":false,\"doc_values\":true,\"searchable\":true,\"aggregatable\":true},{\"name\":\"value.MAX_CONTINUOUS_MEAN\",\"type\":\"number\",\"count\":0,\"scripted\":false,\"indexed\":true,\"analyzed\":false,\"doc_values\":true,\"searchable\":true,\"aggregatable\":true},{\"name\":\"value.WRITES\",\"type\":\"number\",\"count\":0,\"scripted\":false,\"indexed\":true,\"analyzed\":false,\"doc_values\":true,\"searchable\":true,\"aggregatable\":true},{\"name\":\"value.SUM_CONTINUOUS_N\",\"type\":\"number\",\"count\":0,\"scripted\":false,\"indexed\":true,\"analyzed\":false,\"doc_values\":true,\"searchable\":true,\"aggregatable\":true},{\"name\":\"value.SYSTEM_NONHEAP\",\"type\":\"number\",\"count\":0,\"scripted\":false,\"indexed\":true,\"analyzed\":false,\"doc_values\":true,\"searchable\":true,\"aggregatable\":true},{\"name\":\"value.TOTAL_PAGES\",\"type\":\"number\",\"count\":0,\"scripted\":false,\"indexed\":true,\"analyzed\":false,\"doc_values\":true,\"searchable\":true,\"aggregatable\":true},{\"name\":\"value.AVG_NUM_OF_PARTITIONS\",\"type\":\"number\",\"count\":0,\"scripted\":false,\"indexed\":true,\"analyzed\":false,\"doc_values\":true,\"searchable\":true,\"aggregatable\":true},{\"name\":\"logicTime\",\"type\":\"date\",\"count\":0,\"scripted\":false,\"indexed\":true,\"analyzed\":false,\"doc_values\":true,\"searchable\":true,\"aggregatable\":true},{\"name\":\"value.AVG_OF_BUCKET_HITS\",\"type\":\"number\",\"count\":0,\"scripted\":false,\"indexed\":true,\"analyzed\":false,\"doc_values\":true,\"searchable\":true,\"aggregatable\":true},{\"name\":\"value.AVG_MAX_CONTINUOUS_N\",\"type\":\"number\",\"count\":0,\"scripted\":false,\"indexed\":true,\"analyzed\":false,\"doc_values\":true,\"searchable\":true,\"aggregatable\":true},{\"name\":\"tags.FLUME_COMPONENT_TYPE\",\"type\":\"string\",\"count\":0,\"scripted\":false,\"indexed\":true,\"analyzed\":false,\"doc_values\":true,\"searchable\":true,\"aggregatable\":true},{\"name\":\"value.FAILED_PAGES\",\"type\":\"number\",\"count\":0,\"scripted\":false,\"indexed\":true,\"analyzed\":false,\"doc_values\":true,\"searchable\":true,\"aggregatable\":true},{\"name\":\"tags.FAILURE_REASON\",\"type\":\"string\",\"count\":0,\"scripted\":false,\"indexed\":true,\"analyzed\":false,\"doc_values\":true,\"searchable\":true,\"aggregatable\":true},{\"name\":\"tags.FEATURE_NAME\",\"type\":\"string\",\"count\":0,\"scripted\":false,\"indexed\":true,\"analyzed\":false,\"doc_values\":true,\"searchable\":true,\"aggregatable\":true},{\"name\":\"value.AGGREGATIONS\",\"type\":\"number\",\"count\":0,\"scripted\":false,\"indexed\":true,\"analyzed\":false,\"doc_values\":true,\"searchable\":true,\"aggregatable\":true},{\"name\":\"value.AVG_CONTINUOUS_SD\",\"type\":\"number\",\"count\":0,\"scripted\":false,\"indexed\":true,\"analyzed\":false,\"doc_values\":true,\"searchable\":true,\"aggregatable\":true},{\"name\":\"value.SYSTEM_NONHEAP_COMMITTED\",\"type\":\"number\",\"count\":0,\"scripted\":false,\"indexed\":true,\"analyzed\":false,\"doc_values\":true,\"searchable\":true,\"aggregatable\":true},{\"name\":\"value.FEATURE_BUCKETS_UPDATES\",\"type\":\"number\",\"count\":0,\"scripted\":false,\"indexed\":true,\"analyzed\":false,\"doc_values\":true,\"searchable\":true,\"aggregatable\":true},{\"name\":\"value.AMOUNT_OF_ALL_DATA_FILTERED\",\"type\":\"number\",\"count\":0,\"scripted\":false,\"indexed\":true,\"analyzed\":false,\"doc_values\":true,\"searchable\":true,\"aggregatable\":true},{\"name\":\"tags.FLUME_COMPONENT_INSTANCE_ID\",\"type\":\"string\",\"count\":0,\"scripted\":false,\"indexed\":true,\"analyzed\":false,\"doc_values\":true,\"searchable\":true,\"aggregatable\":true},{\"name\":\"name\",\"type\":\"string\",\"count\":0,\"scripted\":false,\"indexed\":true,\"analyzed\":false,\"doc_values\":true,\"searchable\":true,\"aggregatable\":true},{\"name\":\"value.SYSTEM_CPU_TIME\",\"type\":\"number\",\"count\":0,\"scripted\":false,\"indexed\":true,\"analyzed\":false,\"doc_values\":true,\"searchable\":true,\"aggregatable\":true},{\"name\":\"value.MAX_SCORE\",\"type\":\"number\",\"count\":0,\"scripted\":false,\"indexed\":true,\"analyzed\":false,\"doc_values\":true,\"searchable\":true,\"aggregatable\":true},{\"name\":\"value.MAX_FEATURE_VALUE\",\"type\":\"number\",\"count\":0,\"scripted\":false,\"indexed\":true,\"analyzed\":false,\"doc_values\":true,\"searchable\":true,\"aggregatable\":true},{\"name\":\"value.MAX_NUM_OF_PARTITIONS\",\"type\":\"number\",\"count\":0,\"scripted\":false,\"indexed\":true,\"analyzed\":false,\"doc_values\":true,\"searchable\":true,\"aggregatable\":true},{\"name\":\"value.DEFAULT_METRIC_VALUE\",\"type\":\"number\",\"count\":0,\"scripted\":false,\"indexed\":true,\"analyzed\":false,\"doc_values\":true,\"searchable\":true,\"aggregatable\":true},{\"name\":\"value.SUM_RESOLUTION\",\"type\":\"number\",\"count\":0,\"scripted\":false,\"indexed\":true,\"analyzed\":false,\"doc_values\":true,\"searchable\":true,\"aggregatable\":true},{\"name\":\"value.SYSTEM_GC_OLD_TIME\",\"type\":\"number\",\"count\":0,\"scripted\":false,\"indexed\":true,\"analyzed\":false,\"doc_values\":true,\"searchable\":true,\"aggregatable\":true},{\"name\":\"tags.ADE_EVENT_TYPE\",\"type\":\"string\",\"count\":0,\"scripted\":false,\"indexed\":true,\"analyzed\":false,\"doc_values\":true,\"searchable\":true,\"aggregatable\":true},{\"name\":\"value.SYSTEM_THREADS_DAEMON\",\"type\":\"number\",\"count\":0,\"scripted\":false,\"indexed\":true,\"analyzed\":false,\"doc_values\":true,\"searchable\":true,\"aggregatable\":true},{\"name\":\"value.AMOUNT_OF_SEGMENT_PRIORS\",\"type\":\"number\",\"count\":0,\"scripted\":false,\"indexed\":true,\"analyzed\":false,\"doc_values\":true,\"searchable\":true,\"aggregatable\":true},{\"name\":\"value.SUM_GLOBAL_SD\",\"type\":\"number\",\"count\":0,\"scripted\":false,\"indexed\":true,\"analyzed\":false,\"doc_values\":true,\"searchable\":true,\"aggregatable\":true},{\"name\":\"value.MAX_OF_SMOOTHED_BUCKETS\",\"type\":\"number\",\"count\":0,\"scripted\":false,\"indexed\":true,\"analyzed\":false,\"doc_values\":true,\"searchable\":true,\"aggregatable\":true},{\"name\":\"value.AMOUNT_OF_SUCCEEDED_MODELS\",\"type\":\"number\",\"count\":0,\"scripted\":false,\"indexed\":true,\"analyzed\":false,\"doc_values\":true,\"searchable\":true,\"aggregatable\":true},{\"name\":\"tags.UNIT\",\"type\":\"string\",\"count\":0,\"scripted\":false,\"indexed\":true,\"analyzed\":false,\"doc_values\":true,\"searchable\":true,\"aggregatable\":true},{\"name\":\"value.SYSTEM_CPU_LOAD\",\"type\":\"number\",\"count\":0,\"scripted\":false,\"indexed\":true,\"analyzed\":false,\"doc_values\":true,\"searchable\":true,\"aggregatable\":true},{\"name\":\"value.SYSTEM_SYSTEMLOAD_AVERAGE\",\"type\":\"number\",\"count\":0,\"scripted\":false,\"indexed\":true,\"analyzed\":false,\"doc_values\":true,\"searchable\":true,\"aggregatable\":true},{\"name\":\"value.WEIGHT\",\"type\":\"number\",\"count\":0,\"scripted\":false,\"indexed\":true,\"analyzed\":false,\"doc_values\":true,\"searchable\":true,\"aggregatable\":true},{\"name\":\"value.EMPTY_MODEL\",\"type\":\"number\",\"count\":0,\"scripted\":false,\"indexed\":true,\"analyzed\":false,\"doc_values\":true,\"searchable\":true,\"aggregatable\":true},{\"name\":\"value.AVG_SIZE_OF_FEATURE_VALUES\",\"type\":\"number\",\"count\":0,\"scripted\":false,\"indexed\":true,\"analyzed\":false,\"doc_values\":true,\"searchable\":true,\"aggregatable\":true},{\"name\":\"value.AMOUNT_OF_SCORED\",\"type\":\"number\",\"count\":0,\"scripted\":false,\"indexed\":true,\"analyzed\":false,\"doc_values\":true,\"searchable\":true,\"aggregatable\":true},{\"name\":\"tags.SCHEMA\",\"type\":\"string\",\"count\":0,\"scripted\":false,\"indexed\":true,\"analyzed\":false,\"doc_values\":true,\"searchable\":true,\"aggregatable\":true},{\"name\":\"value.AVG_CONTINUOUS_MAX_VALUE\",\"type\":\"number\",\"count\":0,\"scripted\":false,\"indexed\":true,\"analyzed\":false,\"doc_values\":true,\"searchable\":true,\"aggregatable\":true},{\"name\":\"value.MAX_CONTINUOUS_SD\",\"type\":\"number\",\"count\":0,\"scripted\":false,\"indexed\":true,\"analyzed\":false,\"doc_values\":true,\"searchable\":true,\"aggregatable\":true},{\"name\":\"value.SUM_MAX_CONTINUOUS_SD\",\"type\":\"number\",\"count\":0,\"scripted\":false,\"indexed\":true,\"analyzed\":false,\"doc_values\":true,\"searchable\":true,\"aggregatable\":true},{\"name\":\"value.MAX_MAX_CONTINUOUS_SD\",\"type\":\"number\",\"count\":0,\"scripted\":false,\"indexed\":true,\"analyzed\":false,\"doc_values\":true,\"searchable\":true,\"aggregatable\":true},{\"name\":\"value.AVG_CONTINUOUS_N\",\"type\":\"number\",\"count\":0,\"scripted\":false,\"indexed\":true,\"analyzed\":false,\"doc_values\":true,\"searchable\":true,\"aggregatable\":true},{\"name\":\"value.MAX_MEAN\",\"type\":\"number\",\"count\":0,\"scripted\":false,\"indexed\":true,\"analyzed\":false,\"doc_values\":true,\"searchable\":true,\"aggregatable\":true},{\"name\":\"tags.MODEL\",\"type\":\"string\",\"count\":0,\"scripted\":false,\"indexed\":true,\"analyzed\":false,\"doc_values\":true,\"searchable\":true,\"aggregatable\":true},{\"name\":\"value.AMOUNT_OF_CONTEXTS\",\"type\":\"number\",\"count\":0,\"scripted\":false,\"indexed\":true,\"analyzed\":false,\"doc_values\":true,\"searchable\":true,\"aggregatable\":true},{\"name\":\"value.SYSTEM_THREADS\",\"type\":\"number\",\"count\":0,\"scripted\":false,\"indexed\":true,\"analyzed\":false,\"doc_values\":true,\"searchable\":true,\"aggregatable\":true},{\"name\":\"tags.RESULT\",\"type\":\"string\",\"count\":0,\"scripted\":false,\"indexed\":true,\"analyzed\":false,\"doc_values\":true,\"searchable\":true,\"aggregatable\":true},{\"name\":\"value.AVG_OF_SMOOTHED_BUCKETS\",\"type\":\"number\",\"count\":0,\"scripted\":false,\"indexed\":true,\"analyzed\":false,\"doc_values\":true,\"searchable\":true,\"aggregatable\":true},{\"name\":\"value.SUM_MAX_CONTINUOUS_MEAN\",\"type\":\"number\",\"count\":0,\"scripted\":false,\"indexed\":true,\"analyzed\":false,\"doc_values\":true,\"searchable\":true,\"aggregatable\":true},{\"name\":\"value.AVG\",\"type\":\"number\",\"count\":0,\"scripted\":false,\"indexed\":true,\"analyzed\":false,\"doc_values\":true,\"searchable\":true,\"aggregatable\":true},{\"name\":\"_id\",\"type\":\"string\",\"count\":0,\"scripted\":false,\"indexed\":false,\"analyzed\":false,\"doc_values\":false,\"searchable\":false,\"aggregatable\":false},{\"name\":\"_type\",\"type\":\"string\",\"count\":0,\"scripted\":false,\"indexed\":false,\"analyzed\":false,\"doc_values\":false,\"searchable\":false,\"aggregatable\":false},{\"name\":\"_index\",\"type\":\"string\",\"count\":0,\"scripted\":false,\"indexed\":false,\"analyzed\":false,\"doc_values\":false,\"searchable\":false,\"aggregatable\":false},{\"name\":\"_score\",\"type\":\"number\",\"count\":0,\"scripted\":false,\"indexed\":false,\"analyzed\":false,\"doc_values\":false,\"searchable\":false,\"aggregatable\":false}]"
  }
}